Workbook

Sheet Inputs
A1: Event Budget Inputs
A2: Edit yellow cells. Blue and green cells contain formulas or calculated outputs.
A4: Input | B4: Value | C4: Notes
A5: Event name | B5: Stavanger Student Golf Invitational | C5: Name used in the workbook
A6: Venue | B6: Sola GK | C6: Course or venue
A7: Total players | B7: 72 | C7: Maximum planned field
A8: Company share | B8: 0.25 | C8: Share of places included in company packages
A9: Company players | B9: =ROUND(B7*B8,0) -> 18 | C9: Calculated
A10: Paying students | B10: =B7-B9 -> 54 | C10: Calculated
A11: Contingency rate | B11: 0.1 | C11: Applied to cash expenses
A12: Target cash sponsorship | B12: 135000 | C12: Do not include in-kind prizes
A13: Provisional student fee | B13: 900 | C13: Public registration price
A16: Budget result | B16: Value | C16: Meaning
A17: Expense subtotal | B17: =Costs!E19 -> 163400 | C17: Before contingency
A18: Contingency | B18: =Costs!E20 -> 16340 | C18: Reserve for uncertainty
A19: Working total | B19: =Costs!E21 -> 179740 | C19: Total cash requirement
A20: Package revenue | B20: =Sponsorship!F10 -> 135000 | C20: Revenue from package allocation
A21: Company places allocated | B21: =Sponsorship!E10 -> 18 | C21: Must not exceed company-player capacity
A22: Funding after package revenue | B22: =B19-B20 -> 44740 | C22: Amount remaining for student fees or other income
A23: Break-even student fee | B23: =IF(B10=0,0,MAX(0,B22/B10)) -> 828.51852 | C23: Required fee using package revenue
A24: Projected student revenue | B24: =B10*B13 -> 48600 | C24: At full attendance
A25: Projected result | B25: =B20+B24-B19 -> 3860 | C25: Positive is surplus; negative is funding gap

Sheet Costs
A1: Event Costs
A2: Enter quantities and unit costs. Use zero for sponsor-supplied items with no event cash expense.
A4: Category | B4: Cost item | C4: Quantity | D4: Unit cost | E4: Total | F4: Status / notes
A5: Venue | B5: Fixed venue charge | C5: 1 | D5: 17000 | E5: =C5*D5 -> 17000 | F5: Provided; confirm scope, VAT and terms
A6: Golf | B6: Green fees | C6: 72 | D6: 900 | E6: =C6*D6 -> 64800 | F6: Provided; confirm VAT and minimum commitment
A7: Food | B7: Dinner/food | C7: 72 | D7: 450 | E7: =C7*D7 -> 32400 | F7: Working midpoint of NOK 400-500
A8: Food | B8: On-course refreshments | C8: 72 | D8: 100 | E8: =C8*D8 -> 7200 | F8: Planning allowance
A9: Evening | B9: Dinner/afterparty room and AV | C9: 1 | D9: 10000 | E9: =C9*D9 -> 10000 | F9: Estimate; may be included in venue or catering
A10: Prizes | B10: Competition and main prizes | C10: 1 | D10: 0 | E10: =C10*D10 -> 0 | F10: Non-cash items supplied by sponsors
A11: Production | B11: Signs, badges, scorecards and stands | C11: 1 | D11: 5000 | E11: =C11*D11 -> 5000 | F11: Planning allowance
A12: Media | B12: Photographer/content | C12: 1 | D12: 8000 | E12: =C12*D12 -> 8000 | F12: Optional planning allowance
A13: Compliance | B13: Insurance, first aid and permits | C13: 1 | D13: 5000 | E13: =C13*D13 -> 5000 | F13: Confirm organizer and venue coverage
A14: Digital | B14: Website, payment and administration | C14: 1 | D14: 5000 | E14: =C14*D14 -> 5000 | F14: Excludes development labor
A15: Operations | B15: Event staff/volunteer expenses | C15: 1 | D15: 6000 | E15: =C15*D15 -> 6000 | F15: Confirm staffing plan
A16: Logistics | B16: Local transport and miscellaneous | C16: 1 | D16: 3000 | E16: =C16*D16 -> 3000 | F16: Planning allowance
... A18: Other | B18: Other expense 2 | C18: 1 | D18: 0 | E18: =C18*D18 -> 0 | F18: Unused allowance
B19: Subtotal | E19: =SUM(E5:E18) -> 163400
B20: Contingency | E20: =E19*Inputs!B11 -> 16340
B21: Working total | E21: =E19+E20 -> 179740

Sheet Sponsorship
A1: Sponsorship Packages
A2: Package places are included benefits, not free event capacity. In-kind prizes are excluded from cash revenue.
A4: Package | B4: Price | C4: Players included | D4: Packages sold | E4: Places allocated | F4: Cash revenue
A5: Title Partner | B5: 30000 | C5: 4 | D5: 1 | E5: =C5*D5 -> 4 | F5: =B5*D5 -> 30000
A6: Company Partner | B6: 15000 | C6: 2 | D6: 5 | E6: =C6*D6 -> 10 | F6: =B6*D6 -> 75000
A7: Supporting Partner | B7: 7500 | C7: 1 | D7: 4 | E7: =C7*D7 -> 4 | F7: =B7*D7 -> 30000
A8: Additional Package | B8: 0 | C8: 0 | D8: 0 | E8: =C8*D8 -> 0 | F8: =B8*D8 -> 0
A9: Additional Package | B9: 0 | C9: 0 | D9: 0 | E9: =C9*D9 -> 0 | F9: =B9*D9 -> 0
A10: TOTAL | E10: =SUM(E5:E9) -> 18 | F10: =SUM(F5:F9) -> 135000
A12: Company-player capacity | E12: =Inputs!B8 -> 0.25
A13: Unallocated / overallocated places | E13: =E12-E10 -> -17.75
A14: Direct event cost per player | E14: =SUMIF(Costs!B5:B18,"Green fees",Costs!D5:D18)+SUMIF(Costs!B5:B18,"Dinner/food",Costs!D5:D18)+SUMIF(Costs!B5:B18,"On-course refreshments",Costs!D5:D18) -> 1450

Sheet Scenarios
A1: Student Fee Scenarios
A2: Change sponsorship values in column A to compare the required fee for paying students.
A4: Cash sponsorship | B4: Working total | C4: Remaining funding | D4: Paying students | E4: Break-even fee per student | F4: Notes
A5: 0 | B5: =Costs!E21 -> 179740 | C5: =MAX(0,B5-A5) -> 179740 | D5: =Inputs!B10 -> 54 | E5: =IF(D5=0,0,C5/D5) -> 3328.5185
A6: 50000 | B6: =Costs!E21 -> 179740 | C6: =MAX(0,B6-A6) -> 129740 | D6: =Inputs!B10 -> 54 | E6: =IF(D6=0,0,C6/D6) -> 2402.5926
A7: 75000 | B7: =Costs!E21 -> 179740 | C7: =MAX(0,B7-A7) -> 104740 | D7: =Inputs!B10 -> 54 | E7: =IF(D7=0,0,C7/D7) -> 1939.6296
A8: 100000 | B8: =Costs!E21 -> 179740 | C8: =MAX(0,B8-A8) -> 79740 | D8: =Inputs!B10 -> 54 | E8: =IF(D8=0,0,C8/D8) -> 1476.6667
A9: 125000 | B9: =Costs!E21 -> 179740 | C9: =MAX(0,B9-A9) -> 54740 | D9: =Inputs!B10 -> 54 | E9: =IF(D9=0,0,C9/D9) -> 1013.7037
A10: 135000 | B10: =Costs!E21 -> 179740 | C10: =MAX(0,B10-A10) -> 44740 | D10: =Inputs!B10 -> 54 | E10: =IF(D10=0,0,C10/D10) -> 828.51852
